[
{
    "id":1,
    "name": "Damas Center",
    "daysOff": ['Friday', 'Saturday'],
    "openAt": "8",
    "closeAt": "16",
    "coordinates":{"latitude":"33.5118336","longitude":"36.2774528"}
},
{
    "id":2,
    "name": "Aleppo Center",
    "daysOff": ['Friday', 'Saturday'],
    "openAt": "8",
    "closeAt": "16",
    "coordinates":{"latitude":"33.5118336","longitude":"36.2774528"}
},
{
    "id":3,
    "name": "Latakia Center",
    "daysOff": ['Friday', 'Saturday'],
    "openAt": "8",
    "closeAt": "16",
    "coordinates":{"latitude":"33.5118336","longitude":"36.2774528"}
},
]
